Workbook

Sheet Order
A1: MID-TIER INDIAN RETAIL COMPANY
A2: Order_ID | B2: Order_date | C2: Religion | D2: City | E2: Product_Category | F2: Product_Name | G2: Unit_Sold | H2: Unit_Price | I2: Cost_Price | J2: Sales_Amount | K2: Profit
A3: Order01 | B3: 45748 | C3: North | D3: Delhi | E3: Mobile | F3: Samsung A-Series | G3: 2300 | H3: 22000 | I3: 11000 | J3: =H3*G3 -> 50600000 | K3: =J3-(I3*G3) -> 25300000
A4: Order02 | B4: 45749 | C4: East | D4: Noida | E4: Accessories | F4: Samsung A-series | G4: 45200 | H4: 2200 | I4: 1100 | J4: =H4*G4 -> 99440000 | K4: =J4-(I4*G4) -> 49720000
A5: Order03 | B5: 45750 | C5: North | D5: G.Noida | E5: Laptop | F5: Apple | G5: 1000 | H5: 85000 | I5: 66000 | J5: =H5*G5 -> 85000000 | K5: =J5-(I5*G5) -> 19000000
A6: Order04 | B6: 45751 | C6: West | D6: Gaziyabad | E6: Laptop | F6: lenovo | G6: 25650 | H6: 35000 | I6: 13000 | J6: =H6*G6 -> 897750000 | K6: =J6-(I6*G6) -> 564300000
A7: Order05 | B7: 45752 | C7: East | D7: Gaziyabad | E7: Laptop | F7: Asus | G7: 1234 | H7: 64500 | I7: 45000 | J7: =H7*G7 -> 79593000 | K7: =J7-(I7*G7) -> 24063000
A8: Order06 | B8: 45753 | C8: South | D8: Noida | E8: Mobile | F8: Vivo Y-Series | G8: 25640 | H8: 24000 | I8: 15200 | J8: =H8*G8 -> 615360000 | K8: =J8-(I8*G8) -> 225632000
A9: Order07 | B9: 45754 | C9: East | D9: G.Noida | E9: Accessories | F9: Vivo N-Series | G9: 8907 | H9: 30000 | I9: 17000 | J9: =H9*G9 -> 267210000 | K9: =J9-(I9*G9) -> 115791000
A10: Order08 | B10: 45755 | C10: South | D10: Delhi | E10: Laptop | F10: Apple | G10: 6805 | H10: 85000 | I10: 66000 | J10: =H10*G10 -> 578425000 | K10: =J10-(I10*G10) -> 129295000
A11: Order09 | B11: 45756 | C11: West | D11: Noida | E11: Mobile | F11: Oppo Reno-Series | G11: 41012 | H11: 27000 | I11: 16000 | J11: =H11*G11 -> 1107324000 | K11: =J11-(I11*G11) -> 451132000
A12: Order10 | B12: 45757 | C12: North | D12: G.Noida | E12: Accessories | F12: Google pixel | G12: 3425 | H12: 4200 | I12: 2500 | J12: =H12*G12 -> 14385000 | K12: =J12-(I12*G12) -> 5822500
A13: Order11 | B13: 45758 | C13: West | D13: Delhi | E13: Laptop | F13: Dell | G13: 6070 | H13: 54000 | I13: 30000 | J13: =H13*G13 -> 327780000 | K13: =J13-(I13*G13) -> 145680000
A14: Order12 | B14: 45759 | C14: South | D14: Noida | E14: Accessories | F14: Oneplus Nord | G14: 4067 | H14: 1800 | I14: 900 | J14: =H14*G14 -> 7320600 | K14: =J14-(I14*G14) -> 3660300
... A52: Order50 | B52: 45797 | C52: South | D52: Delhi | E52: Laptop | F52: lenovo | G52: 21456 | H52: 35000 | I52: 13000 | J52: =H52*G52 -> 750960000 | K52: =J52-(I52*G52) -> 472032000
A53: Order51 | B53: 45798 | C53: East | D53: Noida | E53: Laptop | F53: hp | G53: 25940 | H53: {=_xlfn.XLOOKUP(1,(Product_Master!A:A=E3)*(Product_Master!B:B=F3),Product_Master!C:C)} -> 2300 | I53: {=_xlfn.XLOOKUP(1,(Product_Master!B:B=F3)*(Product_Master!C:C=G3),Product_Master!D:D)} -> 22000 | J53: =H53*G53 -> 59662000 | K53: =J53-(I53*G53) -> -511018000
A54: Order52 | B54: 45799 | C54: South | D54: G.Noida | E54: Mobile | F54: Realme Narzo-Series | G54: 24561 | H54: {=_xlfn.XLOOKUP(1,(Product_Master!A:A=E4)*(Product_Master!B:B=F4),Product_Master!C:C)} -> 45200 | I54: {=_xlfn.XLOOKUP(1,(Product_Master!B:B=F4)*(Product_Master!C:C=G4),Product_Master!D:D)} -> 2200 | J54: =H54*G54 -> 1110157200 | K54: =J54-(I54*G54) -> 1056123000
A55: Order53 | B55: 45800 | C55: North | D55: Gaziyabad | E55: Mobile | F55: Realme Narzo-Series | G55: 245661 | H55: {=_xlfn.XLOOKUP(1,(Product_Master!A:A=E5)*(Product_Master!B:B=F5),Product_Master!C:C)} -> 1000 | I55: {=_xlfn.XLOOKUP(1,(Product_Master!B:B=F5)*(Product_Master!C:C=G5),Product_Master!D:D)} -> 85000 | J55: =H55*G55 -> 245661000 | K55: =J55-(I55*G55) -> -20635524000
A56: Order54 | B56: 45801 | C56: West | D56: G.Noida | E56: Mobile | F56: Techno Pova-series | G56: 25610 | H56: {=_xlfn.XLOOKUP(1,(Product_Master!A:A=E6)*(Product_Master!B:B=F6),Product_Master!C:C)} -> 25650 | I56: {=_xlfn.XLOOKUP(1,(Product_Master!B:B=F6)*(Product_Master!C:C=G6),Product_Master!D:D)} -> 35000 | J56: =H56*G56 -> 656896500 | K56: =J56-(I56*G56) -> -239453500
A57: Order55 | B57: 45802 | C57: South | D57: G.Noida | E57: Laptop | F57: asus | G57: 245610 | H57: {=_xlfn.XLOOKUP(1,(Product_Master!A:A=E7)*(Product_Master!B:B=F7),Product_Master!C:C)} -> 1234 | I57: {=_xlfn.XLOOKUP(1,(Product_Master!B:B=F7)*(Product_Master!C:C=G7),Product_Master!D:D)} -> 64500 | J57: =H57*G57 -> 303082740 | K57: =J57-(I57*G57) -> -15538762260
A58: Order56 | B58: 45803 | C58: East | D58: Delhi | E58: Laptop | F58: dell | G58: 246610 | H58: {=_xlfn.XLOOKUP(1,(Product_Master!A:A=E8)*(Product_Master!B:B=F8),Product_Master!C:C)} -> 25640 | I58: {=_xlfn.XLOOKUP(1,(Product_Master!B:B=F8)*(Product_Master!C:C=G8),Product_Master!D:D)} -> 24000 | J58: =H58*G58 -> 6323080400 | K58: =J58-(I58*G58) -> 404440400
A59: Order57 | B59: 45804 | C59: South | D59: Noida | E59: Accessories | F59: Vivo Y-Series | G59: 246510 | H59: {=_xlfn.XLOOKUP(1,(Product_Master!A:A=E9)*(Product_Master!B:B=F9),Product_Master!C:C)} -> 8907 | I59: {=_xlfn.XLOOKUP(1,(Product_Master!B:B=F9)*(Product_Master!C:C=G9),Product_Master!D:D)} -> 30000 | J59: =H59*G59 -> 2195664570 | K59: =J59-(I59*G59) -> -5199635430
A60: Order58 | B60: 45805 | C60: North | D60: G.Noida | E60: Laptop | F60: asus | G60: 24561 | H60: {=_xlfn.XLOOKUP(1,(Product_Master!A:A=E10)*(Product_Master!B:B=F10),Product_Master!C:C)} -> 6805 | I60: {=_xlfn.XLOOKUP(1,(Product_Master!B:B=F10)*(Product_Master!C:C=G10),Product_Master!D:D)} -> 85000 | J60: =H60*G60 -> 167137605 | K60: =J60-(I60*G60) -> -1920547395
A61: Order59 | B61: 45806 | C61: West | D61: Gaziyabad | E61: Mobile | F61: Oppo Find-Series | G61: 145620 | H61: {=_xlfn.XLOOKUP(1,(Product_Master!A:A=E11)*(Product_Master!B:B=F11),Product_Master!C:C)} -> 41012 | I61: {=_xlfn.XLOOKUP(1,(Product_Master!B:B=F11)*(Product_Master!C:C=G11),Product_Master!D:D)} -> 27000 | J61: =H61*G61 -> 5972167440 | K61: =J61-(I61*G61) -> 2040427440
A62: Order60 | B62: 45807 | C62: South | D62: G.Noida | E62: Accessories | F62: Realme Narzo-Series | G62: 245610 | H62: {=_xlfn.XLOOKUP(1,(Product_Master!A:A=E12)*(Product_Master!B:B=F12),Product_Master!C:C)} -> 3425 | I62: {=_xlfn.XLOOKUP(1,(Product_Master!B:B=F12)*(Product_Master!C:C=G12),Product_Master!D:D)} -> 4200 | J62: =H62*G62 -> 841214250 | K62: =J62-(I62*G62) -> -190347750
A63: Order61 | B63: 45808 | C63: East | D63: Gaziyabad | E63: Accessories | F63: Realme Narzo-Series | G63: 24598 | H63: {=_xlfn.XLOOKUP(1,(Product_Master!A:A=E13)*(Product_Master!B:B=F13),Product_Master!C:C)} -> 6070 | I63: {=_xlfn.XLOOKUP(1,(Product_Master!B:B=F13)*(Product_Master!C:C=G13),Product_Master!D:D)} -> 54000 | J63: =H63*G63 -> 149309860 | K63: =J63-(I63*G63) -> -1178982140
A64: Order62 | B64: 45809 | C64: South | D64: Gaziyabad | E64: Mobile | F64: Techno Pova-series | G64: 245690 | H64: {=_xlfn.XLOOKUP(1,(Product_Master!A:A=E14)*(Product_Master!B:B=F14),Product_Master!C:C)} -> 4067 | I64: {=_xlfn.XLOOKUP(1,(Product_Master!B:B=F14)*(Product_Master!C:C=G14),Product_Master!D:D)} -> 1800 | J64: =H64*G64 -> 999221230 | K64: =J64-(I64*G64) -> 556979230
... A68: Order66 | B68: 45813 | C68: North | D68: Noida | E68: Laptop | F68: Apple | G68: 3592 | H68: {=_xlfn.XLOOKUP(1,(Product_Master!A:A=E18)*(Product_Master!B:B=F18),Product_Master!C:C)} -> 24501 | I68: {=_xlfn.XLOOKUP(1,(Product_Master!B:B=F18)*(Product_Master!C:C=G18),Product_Master!D:D)} -> 40000 | J68: =H68*G68 -> 88007592 | K68: =J68-(I68*G68) -> -55672408
G70: =SUM(G3:G68) -> 2471526 | J70: =SUM(J2:J68) -> 57838893744 | K70: =SUM(K3:K68) -> -15264817766

Sheet Product_Master
A1: Product_Category | B1: Product_Name | C1: Unit_Sold | D1: Unit_Price | E1: Cost_Price
A2: Mobile | B2: Samsung A-Series | C2: 2300 | D2: 22000 | E2: 11000
A3: Accessories | B3: Samsung A-series | C3: 45200 | D3: 2200 | E3: 1100
A4: Laptop | B4: Apple | C4: 1000 | D4: 85000 | E4: 66000
A5: Laptop | B5: lenovo | C5: 25650 | D5: 35000 | E5: 13000
A6: Laptop | B6: Asus | C6: 1234 | D6: 64500 | E6: 45000
A7: Mobile | B7: Vivo Y-Series | C7: 25640 | D7: 24000 | E7: 15200
A8: Accessories | B8: Vivo N-Series | C8: 8907 | D8: 30000 | E8: 17000
A9: Laptop | B9: Apple | C9: 6805 | D9: 85000 | E9: 66000
A10: Mobile | B10: Oppo Reno-Series | C10: 41012 | D10: 27000 | E10: 16000
A11: Accessories | B11: Google pixel | C11: 3425 | D11: 4200 | E11: 2500
A12: Laptop | B12: Dell | C12: 6070 | D12: 54000 | E12: 30000
A13: Accessories | B13: Oneplus Nord | C13: 4067 | D13: 1800 | E13: 900
... A51: Laptop | B51: lenovo | C51: 21456 | D51: 35000 | E51: 13000

Sheet Analysis
A1: Order_ID | B1: Profit Margin Calculation | C1: Month Extraction | D1: Profitability Status | E1: Sales Category | F1: Data_Quality_Flag | G1: Total Order | H1: Clean Orders | I1: Flagged order | J1: % Data Quality
A2: Order01 | B2: =(Order!K3/Order!J3) -> 0.5 | C2: =TEXT(Order!B3,"MMM-YY") -> Apr-25 | D2: =IF(Order!K3>0,"Profitable", IF(Order!K3<0,"Loss","Break-even")) -> Profitable | E2: =IF(Order!J3>=10000000,"High", IF(Order!J3<=10000000,"Medium","Low")) -> High | F2: =IF(OR(Order!H3/Order!I3>1.5,Order!H3/Order!I3<0.3, ABS(B2)>200), "REVIEW", "OK") -> REVIEW | G2: =COUNTA(A:A)-1 -> 66 | H2: =COUNTIF(F:F,"OK") -> 13 | I2: =COUNTIF(F:F,"REVIEW") -> 53 | J2: =(H2/G2) -> 0.1969697
A3: Order02 | B3: =(Order!K4/Order!J4) -> 0.5 | C3: =TEXT(Order!B4,"MMM-YY") -> Apr-25 | D3: =IF(Order!K4>0,"Profitable", IF(Order!K4<0,"Loss","Break-even")) -> Profitable | E3: =IF(Order!J4>=10000000,"High", IF(Order!J4<=10000000,"Medium","Low")) -> High | F3: =IF(OR(Order!H4/Order!I4>1.5,Order!H4/Order!I4<0.3, ABS(B3)>200), "REVIEW", "OK") -> REVIEW
A4: Order03 | B4: =(Order!K5/Order!J5) -> 0.22352941 | C4: =TEXT(Order!B5,"MMM-YY") -> Apr-25 | D4: =IF(Order!K5>0,"Profitable", IF(Order!K5<0,"Loss","Break-even")) -> Profitable | E4: =IF(Order!J5>=10000000,"High", IF(Order!J5<=10000000,"Medium","Low")) -> High | F4: =IF(OR(Order!H5/Order!I5>1.5,Order!H5/Order!I5<0.3, ABS(B4)>200), "REVIEW", "OK") -> OK
A5: Order04 | B5: =(Order!K6/Order!J6) -> 0.62857143 | C5: =TEXT(Order!B6,"MMM-YY") -> Apr-25 | D5: =IF(Order!K6>0,"Profitable", IF(Order!K6<0,"Loss","Break-even")) -> Profitable | E5: =IF(Order!J6>=10000000,"High", IF(Order!J6<=10000000,"Medium","Low")) -> High | F5: =IF(OR(Order!H6/Order!I6>1.5,Order!H6/Order!I6<0.3, ABS(B5)>200), "REVIEW", "OK") -> REVIEW
A6: Order05 | B6: =(Order!K7/Order!J7) -> 0.30232558 | C6: =TEXT(Order!B7,"MMM-YY") -> Apr-25 | D6: =IF(Order!K7>0,"Profitable", IF(Order!K7<0,"Loss","Break-even")) -> Profitable | E6: =IF(Order!J7>=10000000,"High", IF(Order!J7<=10000000,"Medium","Low")) -> High | F6: =IF(OR(Order!H7/Order!I7>1.5,Order!H7/Order!I7<0.3, ABS(B6)>200), "REVIEW", "OK") -> OK
A7: Order06 | B7: =(Order!K8/Order!J8) -> 0.36666667 | C7: =TEXT(Order!B8,"MMM-YY") -> Apr-25 | D7: =IF(Order!K8>0,"Profitable", IF(Order!K8<0,"Loss","Break-even")) -> Profitable | E7: =IF(Order!J8>=10000000,"High", IF(Order!J8<=10000000,"Medium","Low")) -> High | F7: =IF(OR(Order!H8/Order!I8>1.5,Order!H8/Order!I8<0.3, ABS(B7)>200), "REVIEW", "OK") -> REVIEW
A8: Order07 | B8: =(Order!K9/Order!J9) -> 0.43333333 | C8: =TEXT(Order!B9,"MMM-YY") -> Apr-25 | D8: =IF(Order!K9>0,"Profitable", IF(Order!K9<0,"Loss","Break-even")) -> Profitable | E8: =IF(Order!J9>=10000000,"High", IF(Order!J9<=10000000,"Medium","Low")) -> High | F8: =IF(OR(Order!H9/Order!I9>1.5,Order!H9/Order!I9<0.3, ABS(B8)>200), "REVIEW", "OK") -> REVIEW
A9: Order08 | B9: =(Order!K10/Order!J10) -> 0.22352941 | C9: =TEXT(Order!B10,"MMM-YY") -> Apr-25 | D9: =IF(Order!K10>0,"Profitable", IF(Order!K10<0,"Loss","Break-even")) -> Profitable | E9: =IF(Order!J10>=10000000,"High", IF(Order!J10<=10000000,"Medium","Low")) -> High | F9: =IF(OR(Order!H10/Order!I10>1.5,Order!H10/Order!I10<0.3, ABS(B9)>200), "REVIEW", "OK") -> OK
A10: Order09 | B10: =(Order!K11/Order!J11) -> 0.40740741 | C10: =TEXT(Order!B11,"MMM-YY") -> Apr-25 | D10: =IF(Order!K11>0,"Profitable", IF(Order!K11<0,"Loss","Break-even")) -> Profitable | E10: =IF(Order!J11>=10000000,"High", IF(Order!J11<=10000000,"Medium","Low")) -> High | F10: =IF(OR(Order!H11/Order!I11>1.5,Order!H11/Order!I11<0.3, ABS(B10)>200), "REVIEW", "OK") -> REVIEW
A11: Order10 | B11: =(Order!K12/Order!J12) -> 0.4047619 | C11: =TEXT(Order!B12,"MMM-YY") -> Apr-25 | D11: =IF(Order!K12>0,"Profitable", IF(Order!K12<0,"Loss","Break-even")) -> Profitable | E11: =IF(Order!J12>=10000000,"High", IF(Order!J12<=10000000,"Medium","Low")) -> High | F11: =IF(OR(Order!H12/Order!I12>1.5,Order!H12/Order!I12<0.3, ABS(B11)>200), "REVIEW", "OK") -> REVIEW
A12: Order11 | B12: =(Order!K13/Order!J13) -> 0.44444444 | C12: =TEXT(Order!B13,"MMM-YY") -> Apr-25 | D12: =IF(Order!K13>0,"Profitable", IF(Order!K13<0,"Loss","Break-even")) -> Profitable | E12: =IF(Order!J13>=10000000,"High", IF(Order!J13<=10000000,"Medium","Low")) -> High | F12: =IF(OR(Order!H13/Order!I13>1.5,Order!H13/Order!I13<0.3, ABS(B12)>200), "REVIEW", "OK") -> REVIEW
A13: Order12 | B13: =(Order!K14/Order!J14) -> 0.5 | C13: =TEXT(Order!B14,"MMM-YY") -> Apr-25 | D13: =IF(Order!K14>0,"Profitable", IF(Order!K14<0,"Loss","Break-even")) -> Profitable | E13: =IF(Order!J14>=10000000,"High", IF(Order!J14<=10000000,"Medium","Low")) -> Medium | F13: =IF(OR(Order!H14/Order!I14>1.5,Order!H14/Order!I14<0.3, ABS(B13)>200), "REVIEW", "OK") -> REVIEW
A14: Order13 | B14: =(Order!K15/Order!J15) -> 0.52727273 | C14: =TEXT(Order!B15,"MMM-YY") -> Apr-25 | D14: =IF(Order!K15>0,"Profitable", IF(Order!K15<0,"Loss","Break-even")) -> Profitable | E14: =IF(Order!J15>=10000000,"High", IF(Order!J15<=10000000,"Medium","Low")) -> High | F14: =IF(OR(Order!H15/Order!I15>1.5,Order!H15/Order!I15<0.3, ABS(B14)>200), "REVIEW", "OK") -> REVIEW
... A67: Order66 | B67: =(Order!K68/Order!J68) -> -0.63258643 | C67: =TEXT(Order!B68,"MMM-YY") -> Jun-25 | D67: =IF(Order!K68>0,"Profitable", IF(Order!K68<0,"Loss","Break-even")) -> Loss | E67: =IF(Order!J68>=10000000,"High", IF(Order!J68<=10000000,"Medium","Low")) -> High | F67: =IF(OR(Order!H68/Order!I68>1.5,Order!H68/Order!I68<0.3, ABS(B67)>200), "REVIEW", "OK") -> OK

Sheet Dashboard
A2: COMPANY PERFORMANCE DASHBOARD-MID- TIER RETAIL | E2: Month | F2: Revenue
E3: April | F3: =SUMIFS(Order!J3:J68,Order!B3:B68,">=4/1/2025",Order!B3:B68, "<5/1/2025") -> 29988136160
A4: DATA QUALITY SUMMARY | E4: May | F4: =SUMIFS(Order!J3:J68,Order!B3:B68, ">5/1/2025",Order!B3:B68, "<6/1/2025") -> 25308066065
A5: Total order | B5: =COUNTA(Analysis!A:A) -1 -> 66 | E5: June | F5: =SUMIFS(Order!J3:J68,Order!B3:B68,">=6/1/2025", Order!B3:B68,"<7/1/2025") -> 2010791519
A6: Clean Order | B6: =COUNTIF(Analysis!F:F,"OK") -> 13
A7: Flagged Order | B7: =COUNTIF(Analysis!F:F, "REVIEW") -> 53
A8: Data quality | B8: =B6/B5 -> 0.1969697
A10: KEY METRICS- FULL DATASET
A11: Toatal Revenue | B11: =SUM(Order!J2:J68) -> 57838893744
A12: Total profit | B12: =SUM(Order!K3:K68) -> -15264817766
A13: Avg. Order Value | B13: =B11/B5 -> 8.7634687e+08
A14: Overall Profit Margin% | B14: =B12/B11 -> -0.2639196
A15: Total unit sold | B15: =SUM(Order!G:G) -> 4943052
A16: Profitability order | B16: =COUNTIF(Analysis!D:D,"Profitable") -> 56
A17: Loss-Making order | B17: =COUNTIF(Analysis!D:D, "LOSS") -> 10
A19: KEY METRICS-CLEAN DATASET ONLY
A20: Total Revenue | B20: =SUMIF(Analysis!F:F, "OK",Order!J2:J68) -> 13254139693
A21: Total Profit | B21: =SUMIF(Analysis!F:F, "OK",Order!K2:K68) -> 1152622693
A22: Avg Order Value | B22: =B21/B6 -> 88663284
A23: Overall Profit Margin% | B23: =(B21/B20) -> 0.086963222
A24: Total unit Sold | B24: =SUMIF(Analysis!F:F, "OK", Order!G2:G69) -> 609509
A25: Profitable order | B25: =COUNTIFS(Analysis!D:D, "Profitable", Analysis!F:F, "OK") -> 9
A26: loss- making order | B26: =COUNTIFS(Analysis!D:D,"Loss",Analysis!F:F, "OK") -> 4

Sheet Regional_Analysis
E1: REGIONAL PERFORMNANCE ANALYSIS
A3: Region | B3: Total sales | C3: Total profit | D3: Order count | E3: Average order value | F3: Profit margin % | G3: Rank
A4: North | B4: =SUMIF(Order!C3:C68,"North",Order!J3:J68) -> 3634429197 | C4: =SUMIF(Order!C3:C68,"North",Order!K3:K68) -> -20984653303 | D4: =COUNTIF(Order!C3:C68,"North") -> 14 | E4: =Regional_Analysis!B4/Regional_Analysis!D4 -> 2.5960209e+08 | F4: =(C4/B4) -> -5.7738512 | G4: =RANK(B4,$B$4:$B$7,0) -> 4
A5: South | B5: =SUMIF(Order!C3:C68,"South",Order!J3:J68) -> 10035166296 | C5: =SUMIF(Order!C3:C68,"South",Order!K3:K68) -> -17155981404 | D5: =COUNTIF(Order!C2:C68,"South") -> 18 | E5: =Regional_Analysis!B5/Regional_Analysis!D5 -> 5.5750924e+08 | F5: =C5/B5 -> -1.7095862 | G5: =RANK(B5,$B$4:$B$7,0) -> 3
A6: East | B6: =SUMIF(Order!C3:C68,"East",Order!J3:J68) -> 29224891311 | C6: =SUMIF(Order!C3:C68,"East",Order!K3:K68) -> 17680572251 | D6: =COUNTIF(Order!C3:C68,"East") -> 17 | E6: =Regional_Analysis!B6/Regional_Analysis!D6 -> 1.7191113e+09 | F6: =C6/B6 -> 0.60498334 | G6: =RANK(B6,$B$4:$B$7,0) -> 1
A7: West | B7: =SUMIF(Order!C3:C68,"West",Order!J3:J68) -> 14944406940 | C7: =SUMIF(Order!C3:C68,"West",Order!K3:K68) -> 5195244690 | D7: =COUNTIF(Order!C6:C68,"West") -> 17 | E7: =Regional_Analysis!B7/Regional_Analysis!D7 -> 8.7908276e+08 | F7: =C7/B7 -> 0.34763806 | G7: =RANK(B7,$B$4:$B$7,0) -> 2
A9: TOTAL | B9: =SUM(B4:B7) -> 57838893744 | C9: =SUM(C4:C7) -> -15264817766 | D9: =SUM(D4:D7) -> 66 | E9: =SUM(E4:E7) -> 3.4153053e+09 | F9: =SUM(F4:F8) -> -6.5308159

Sheet Product_Analysis
F1: PRODUCT CATEGORY PERFORMANCE ANALYSIS
A3: Product_category | B3: Total sales | C3: Total profit | D3: Unit sold | E3: Order count | F3: Average order value | G3: Profit margin | H3: Revenue share
A4: Mobile | B4: =SUMIF(Order!E2:E68, "Mobile",Order!J2:J69) -> 16622247067 | C4: =SUMIF(Order!E3:E68,"Mobile",Order!K3:K68) -> -13775490733 | D4: =SUMIF(Order!E2:E68,"Mobile",Order!G2:G68) -> 1010655 | E4: =COUNTIF(Order!E2:E68,"Mobile") -> 23 | F4: =B4/E4 -> 7.2270639e+08 | G4: =C4/B4 -> -0.82873818 | H4: =(B4/$B$8) -> 0.28738874
A5: Laptop | B5: =SUMIF(Order!E2:E68,"Laptop",Order!J2:J68) -> 36058258337 | C5: =SUMIF(Order!E3:E69,"Laptop",Order!K3:K68) -> 4401468337 | D5: =SUMIF(Order!E2:E68,"Laptop",Order!G2:G68) -> 741760 | E5: =COUNTIF(Order!E2:E68,"Laptop") -> 23 | F5: =B5/E5 -> 1.5677504e+09 | G5: =C5/B5 -> 0.12206547 | H5: =(B5/$B$8) -> 0.6234258
A6: Accessories | B6: =SUMIF(Order!E3:E69,"Accessories",Order!J3:J68) -> 5158388340 | C6: =SUMIF(Order!E3:E70,"Accessories",Order!K3:K68) -> -5890795370 | D6: =SUMIF(Order!E2:E68,"Accessories",Order!G2:G68) -> 719111 | E6: =COUNTIF(Order!E2:E68,"Accessories") -> 20 | F6: =B6/E6 -> 257919417 | G6: =C6/B6 -> -1.1419837 | H6: =(B6/$B$8) -> 0.08918546
A8: Total | B8: =SUM(B4:B6) -> 57838893744 | C8: =SUM(C4:C6) -> -15264817766 | D8: =SUM(D4:D7) -> 2471526 | E8: =SUM(E4:E6) -> 66 | F8: =SUM(F4:F6) -> 2.5483762e+09 | G8: =SUM(G4:G6) -> -1.8486564 | H8: =SUM(H4:H6) -> 1

Sheet Executive_Summary
A1: EXECUTIVE SUMMARY
A2: Mid- Tier Indian Retail Company - Sales Performance Analysis
A3: Analysis Period : April - june 2025
A5: PROJECT OVERVIEW
A6: Analysis 66 transaction record across 4 regions and 3 Product categories to assess business performance and identity optimization opportunity
A8: KEY FINDING
A9: Data Quality Crisis
A10: Data audit uncovered critical pricing corruption in 80% of transactions. XLOOKUP- Based data entry process inadvertently reversed cost and selling prices, causing high- value electronics to be recorded at procurement cost rather than retail price. This data quality failure masked actual business performance: contaminated dataset shows negative 26% margin, while validated clean subset reveals healthy positive 9% margin and ₹115Cr profit.
A12: Regional Performance
A13: Regional analysis reveals stark performance divergence: East region leads with 292Cr revenue and 60% profit margin, while North region shows severe losses (577% margin) despite 14 orders. West region ranks second with positive performance. North and south region require immediate data validation, as current metrics systematic pricing error rather than fundamental business issues.
A15: Product Category Analysis
A16: Product Category Analysis identifies laptop as the sole profitable category, generating 62% of revenue "360Cr." with healthy 12% margins. Mobile shows concerning matrics: 10lakh+ units sold but negative margin due to pricing data corruption. Accessories category demonstrates catastrophic (114%) margins. Laptop segment strength indicate sound business fundamentals on pricing data integrity is restored across all categories.
... A36: Analysis Tools: Miicrosoft Excel ( XLOOKUP, Different fuctiion such as sumif, countif, Data validation)
B40: Date: Febuary 10, 2026
